{
    "/jsx/application.js": "/jsx/application.js",
    "/jsx/application.dc3a386029a708a6e358.hot-update.js": "/jsx/application.dc3a386029a708a6e358.hot-update.js",
    "/jsx/application.3923eaf065a69d92772c.hot-update.js": "/jsx/application.3923eaf065a69d92772c.hot-update.js",
    "/jsx/application.984299baa1af8a40a0a9.hot-update.js": "/jsx/application.984299baa1af8a40a0a9.hot-update.js",
    "/jsx/application.366e579954614341b542.hot-update.js": "/jsx/application.366e579954614341b542.hot-update.js"
}
